Workbook

Sheet Resumen
A1: Catálogo de plantillas por tipo de negocio
A2: Base del onboarding automático: el usuario elige su negocio y el sistema activa módulos y precarga su catálogo.
A4: Cómo funciona (3 capas)
A5: 1. Módulos: piezas que se activan o desactivan | C5: Hoja Módulos
A6: 2. Familias: grupos de negocio que comparten módulos | C6: Hojas Familias y Matriz
A7: 3. Tipos de negocio: ficha ligera por negocio | C7: Hoja Tipos de negocio
A9: Totales
A10: Módulos | B10: =COUNTA(Módulos!A2:A27) -> 26
A11: Módulos núcleo (siempre activos) | B11: =COUNTIF(Módulos!D2:D27,"Núcleo") -> 6
A12: Familias | B12: =COUNTA(Familias!A2:A17) -> 16
A13: Tipos de negocio | B13: =COUNTA('Tipos de negocio'!A2:A217) -> 216
A15: Tipos de negocio por familia
A16: Familia | B16: Tipos | C16: Módulos activos
A17: F01 · Restaurantes con servicio a mesa | B17: =COUNTIF('Tipos de negocio'!C$2:C$217,"F01") -> 18 | C17: =COUNTIF(Matriz!C2:AB2,"S") -> 12
A18: F02 · Comida rápida y para llevar | B18: =COUNTIF('Tipos de negocio'!C$2:C$217,"F02") -> 14 | C18: =COUNTIF(Matriz!C3:AB3,"S") -> 10
A19: F03 · Panadería, pastelería y producción | B19: =COUNTIF('Tipos de negocio'!C$2:C$217,"F03") -> 12 | C19: =COUNTIF(Matriz!C4:AB4,"S") -> 11
A20: F04 · Abarrotes y mercado | B20: =COUNTIF('Tipos de negocio'!C$2:C$217,"F04") -> 16 | C20: =COUNTIF(Matriz!C5:AB5,"S") -> 12
A21: F05 · Moda y retail con variantes | B21: =COUNTIF('Tipos de negocio'!C$2:C$217,"F05") -> 12 | C21: =COUNTIF(Matriz!C6:AB6,"S") -> 10
A22: F06 · Retail general | B22: =COUNTIF('Tipos de negocio'!C$2:C$217,"F06") -> 20 | C22: =COUNTIF(Matriz!C7:AB7,"S") -> 9
A23: F07 · Farmacia y salud con producto | B23: =COUNTIF('Tipos de negocio'!C$2:C$217,"F07") -> 6 | C23: =COUNTIF(Matriz!C8:AB8,"S") -> 10
A24: F08 · Tecnología y electrónica | B24: =COUNTIF('Tipos de negocio'!C$2:C$217,"F08") -> 10 | C24: =COUNTIF(Matriz!C9:AB9,"S") -> 10
A25: F09 · Ferretería y construcción | B25: =COUNTIF('Tipos de negocio'!C$2:C$217,"F09") -> 10 | C25: =COUNTIF(Matriz!C10:AB10,"S") -> 13
A26: F10 · Servicios con cita | B26: =COUNTIF('Tipos de negocio'!C$2:C$217,"F10") -> 18 | C26: =COUNTIF(Matriz!C11:AB11,"S") -> 9
A27: F11 · Talleres y servicio técnico | B27: =COUNTIF('Tipos de negocio'!C$2:C$217,"F11") -> 18 | C27: =COUNTIF(Matriz!C12:AB12,"S") -> 11
A28: F12 · Servicios profesionales | B28: =COUNTIF('Tipos de negocio'!C$2:C$217,"F12") -> 15 | C28: =COUNTIF(Matriz!C13:AB13,"S") -> 8
A29: F13 · Mayoristas y distribuidoras | B29: =COUNTIF('Tipos de negocio'!C$2:C$217,"F13") -> 12 | C29: =COUNTIF(Matriz!C14:AB14,"S") -> 12
A30: F14 · Agro y acopio | B30: =COUNTIF('Tipos de negocio'!C$2:C$217,"F14") -> 13 | C30: =COUNTIF(Matriz!C15:AB15,"S") -> 11
A31: F15 · Deporte, educación y membresías | B31: =COUNTIF('Tipos de negocio'!C$2:C$217,"F15") -> 11 | C31: =COUNTIF(Matriz!C16:AB16,"S") -> 8
A32: F16 · Hospedaje, eventos y alquiler | B32: =COUNTIF('Tipos de negocio'!C$2:C$217,"F16") -> 11 | C32: =COUNTIF(Matriz!C17:AB17,"S") -> 9
A34: Primera propuesta para revisar. Los tipos de negocio se amplían (también con IA) sin tocar los módulos.

Sheet Módulos
A1: ID | B1: Módulo | C1: Qué hace | D1: Tipo
A2: M01 | B2: Ventas (punto de venta) | C2: Registrar ventas rápidas, métodos de pago, descuentos, comprobante por WhatsApp o impreso | D2: Núcleo
A3: M02 | B3: Caja | C3: Apertura y cierre de caja, arqueo, descuadres, ingresos y retiros de efectivo | D3: Núcleo
A4: M03 | B4: Gastos | C4: Registro de gastos por categoría | D4: Núcleo
A5: M04 | B5: Inventario | C5: Stock automático (compra suma, venta resta), alertas de stock bajo, conteos | D5: Activable
A6: M05 | B6: Variantes | C6: Tallas, colores y presentaciones por producto | D6: Activable
A7: M06 | B7: Venta por peso/medida | C7: Venta por kilo, libra, litro, metro, quintal; balanza | D7: Activable
A8: M07 | B8: Código de barras | C8: Lectura EAN-13/UPC-A con cámara o lector, impresión de etiquetas | D8: Activable
A9: M08 | B9: Recetas e insumos | C9: El producto final descuenta insumos; costo por plato o producto | D9: Activable
A10: M09 | B10: Mesas y comandas | C10: Mapa de mesas, cuentas abiertas, comandas a cocina, división de cuenta | D10: Activable
A11: M10 | B11: Pedidos y delivery | C11: Pedidos para llevar o a domicilio, estados, repartidor | D11: Activable
A12: M11 | B12: Citas y agenda | C12: Agenda por profesional, recordatorios por WhatsApp | D12: Activable
... A27: M26 | B27: Reservas por fecha | C27: Reserva de habitaciones, canchas, salones o artículos por fecha/hora | D27: Activable
B29: Núcleo = activo en todos los negocios. Activable = depende de la familia.

Sheet Familias
A1: ID | B1: Familia | C1: Descripción | D1: Palabra para ítems | E1: Unidad por defecto | F1: Módulos que se activan (además del núcleo) | G1: Módulos opcionales
A2: F01 | B2: Restaurantes con servicio a mesa | C2: Atención en mesa, cocina con comandas | D2: Platos | E2: Unidad | F2: Inventario, Recetas e insumos, Mesas y comandas, Pedidos y delivery, Fiado / cuentas por cobrar, Proveedores y compras | G2: Catálogo online, Lotes y caducidad
A3: F02 | B3: Comida rápida y para llevar | C3: Venta rápida en mostrador, combos, delivery | D3: Productos | E3: Unidad | F3: Inventario, Recetas e insumos, Pedidos y delivery, Proveedores y compras | G3: Mesas y comandas, Fiado / cuentas por cobrar, Catálogo online
A4: F03 | B4: Panadería, pastelería y producción | C4: Producen lo que venden; recetas e insumos | D4: Productos | E4: Unidad | F4: Inventario, Recetas e insumos, Fiado / cuentas por cobrar, Proveedores y compras, Lotes y caducidad | G4: Pedidos y delivery, Catálogo online, Cotizaciones
A5: F04 | B5: Abarrotes y mercado | C5: Muchos productos, fiado, venta por peso | D5: Productos | E5: Unidad | F5: Inventario, Venta por peso/medida, Código de barras, Fiado / cuentas por cobrar, Proveedores y compras, Lotes y caducidad | G5: Listas de precios, Catálogo online
A6: F05 | B6: Moda y retail con variantes | C6: Tallas y colores, temporadas | D6: Productos | E6: Unidad | F6: Inventario, Variantes, Código de barras, Proveedores y compras | G6: Fiado / cuentas por cobrar, Listas de precios, Catálogo online
A7: F06 | B7: Retail general | C7: Tiendas y bazares sin variantes complejas | D7: Productos | E7: Unidad | F7: Inventario, Código de barras, Proveedores y compras | G7: Variantes, Fiado / cuentas por cobrar, Listas de precios, Catálogo online
A8: F07 | B8: Farmacia y salud con producto | C8: Lotes, caducidad, control de medicamentos | D8: Productos | E8: Unidad | F8: Inventario, Código de barras, Proveedores y compras, Lotes y caducidad | G8: Fiado / cuentas por cobrar, Listas de precios
A9: F08 | B9: Tecnología y electrónica | C9: Series/IMEI, garantías, servicio técnico | D9: Productos | E9: Unidad | F9: Inventario, Código de barras, Proveedores y compras, Series y garantías | G9: Órdenes de trabajo, Fiado / cuentas por cobrar, Cotizaciones
A10: F09 | B10: Ferretería y construcción | C10: Miles de ítems, medidas, proformas, crédito | D10: Productos | E10: Unidad | F10: Inventario, Venta por peso/medida, Código de barras, Fiado / cuentas por cobrar, Proveedores y compras, Listas de precios, Cotizaciones | G10: Catálogo online
A11: F10 | B11: Servicios con cita | C11: Belleza, bienestar y salud con agenda | D11: Servicios | E11: Servicio | F11: Citas y agenda, Servicios y comisiones, Fiado / cuentas por cobrar | G11: Inventario, Catálogo online
A12: F11 | B12: Talleres y servicio técnico | C12: Órdenes de trabajo, repuestos y mano de obra | D12: Servicios | E12: Servicio | F12: Inventario, Órdenes de trabajo, Fiado / cuentas por cobrar, Proveedores y compras, Cotizaciones | G12: Servicios y comisiones
... A17: F16 | B17: Hospedaje, eventos y alquiler | C17: Reservas por fecha y alquiler de artículos | D17: Servicios | E17: Noche | F17: Fiado / cuentas por cobrar, Cotizaciones, Reservas por fecha | G17: Inventario, Pedidos y delivery

Sheet Matriz
A1: ID | B1: Familia | C1: M01 Ventas (punto de venta) | D1: M02 Caja | E1: M03 Gastos | F1: M04 Inventario | G1: M05 Variantes | H1: M06 Venta por peso/medida | I1: M07 Código de barras | J1: M08 Recetas e insumos | K1: M09 Mesas y comandas | L1: M10 Pedidos y delivery | M1: M11 Citas y agenda | N1: M12 Servicios y comisiones | O1: M13 Órdenes de trabajo | P1: M14 Fiado / cuentas por cobrar | Q1: M15 Proveedores y compras | R1: M16 Lotes y caducidad | S1: M17 Listas de precios | T1: M18 Catálogo online | U1: M19 Facturación electrónica SRI | V1: M20 Empleados y permisos | W1: M21 Reportes y estadísticas | X1: M22 Membresías y planes | Y1: M23 Series y garantías | Z1: M24 Cotizaciones | AA1: M25 Compras a productores (acopio) | AB1: M26 Reservas por fecha
A2: F01 | B2: Restaurantes con servicio a mesa | C2: S | D2: S | E2: S | F2: S | J2: S | K2: S | L2: S | P2: S | Q2: S | R2: O | T2: O | U2: S | V2: S | W2: S
A3: F02 | B3: Comida rápida y para llevar | C3: S | D3: S | E3: S | F3: S | J3: S | K3: O | L3: S | P3: O | Q3: S | T3: O | U3: S | V3: S | W3: S
A4: F03 | B4: Panadería, pastelería y producción | C4: S | D4: S | E4: S | F4: S | J4: S | L4: O | P4: S | Q4: S | R4: S | T4: O | U4: S | V4: S | W4: S | Z4: O
A5: F04 | B5: Abarrotes y mercado | C5: S | D5: S | E5: S | F5: S | H5: S | I5: S | P5: S | Q5: S | R5: S | S5: O | T5: O | U5: S | V5: S | W5: S
A6: F05 | B6: Moda y retail con variantes | C6: S | D6: S | E6: S | F6: S | G6: S | I6: S | P6: O | Q6: S | S6: O | T6: O | U6: S | V6: S | W6: S
A7: F06 | B7: Retail general | C7: S | D7: S | E7: S | F7: S | G7: O | I7: S | P7: O | Q7: S | S7: O | T7: O | U7: S | V7: S | W7: S
A8: F07 | B8: Farmacia y salud con producto | C8: S | D8: S | E8: S | F8: S | I8: S | P8: O | Q8: S | R8: S | S8: O | U8: S | V8: S | W8: S
A9: F08 | B9: Tecnología y electrónica | C9: S | D9: S | E9: S | F9: S | I9: S | O9: O | P9: O | Q9: S | U9: S | V9: S | W9: S | Y9: S | Z9: O
A10: F09 | B10: Ferretería y construcción | C10: S | D10: S | E10: S | F10: S | H10: S | I10: S | P10: S | Q10: S | S10: S | T10: O | U10: S | V10: S | W10: S | Z10: S
A11: F10 | B11: Servicios con cita | C11: S | D11: S | E11: S | F11: O | M11: S | N11: S | P11: S | T11: O | U11: S | V11: S | W11: S
A12: F11 | B12: Talleres y servicio técnico | C12: S | D12: S | E12: S | F12: S | N12: O | O12: S | P12: S | Q12: S | U12: S | V12: S | W12: S | Z12: S
A13: F12 | B13: Servicios profesionales | C13: S | D13: S | E13: S | M13: O | P13: S | U13: S | V13: S | W13: S | Z13: S
A14: F13 | B14: Mayoristas y distribuidoras | C14: S | D14: S | E14: S | F14: S | H14: O | I14: S | P14: S | Q14: S | R14: O | S14: S | T14: O | U14: S | V14: S | W14: S | Z14: S
A15: F14 | B15: Agro y acopio | C15: S | D15: S | E15: S | F15: S | H15: S | P15: S | Q15: S | R15: S | S15: O | U15: S | V15: S | W15: S | AA15: O
A16: F15 | B16: Deporte, educación y membresías | C16: S | D16: S | E16: S | F16: O | M16: O | P16: S | U16: S | V16: S | W16: S | X16: S | AB16: O
A17: F16 | B17: Hospedaje, eventos y alquiler | C17: S | D17: S | E17: S | F17: O | L17: O | P17: S | U17: S | V17: S | W17: S | Z17: S | AB17: S
B19: S = se activa al registrarse
B20: O = se sugiere activar después
B21: Módulos núcleo activos en todas las familias

Sheet Tipos de negocio
A1: ID | B1: Tipo de negocio | C1: Familia ID | D1: Familia | E1: Sinónimos (buscador) | F1: Categorías iniciales | G1: Palabra para ítems | H1: Unidad principal | I1: Ajuste propio
A2: T001 | B2: Restaurante | C2: F01 | D2: =INDEX(Familias!B$2:B$17,MATCH(C2,Familias!A$2:A$17,0)) -> Restaurantes con servicio a mesa | E2: almuerzos, comedor | F2: Entradas; Platos fuertes; Bebidas; Postres | G2: Platos | H2: Unidad
A3: T002 | B3: Cevichería | C3: F01 | D3: =INDEX(Familias!B$2:B$17,MATCH(C3,Familias!A$2:A$17,0)) -> Restaurantes con servicio a mesa | E3: ceviche, mariscos | F3: Ceviches; Mariscos; Bebidas; Acompañantes | G3: Platos | H3: Unidad
A4: T003 | B4: Marisquería | C4: F01 | D4: =INDEX(Familias!B$2:B$17,MATCH(C4,Familias!A$2:A$17,0)) -> Restaurantes con servicio a mesa | E4: mariscos | F4: Encocados; Arroces; Ceviches; Bebidas | G4: Platos | H4: Unidad
A5: T004 | B5: Picantería | C5: F01 | D5: =INDEX(Familias!B$2:B$17,MATCH(C5,Familias!A$2:A$17,0)) -> Restaurantes con servicio a mesa | E5: comida típica | F5: Platos típicos; Bebidas; Entradas | G5: Platos | H5: Unidad
A6: T005 | B6: Asadero | C6: F01 | D6: =INDEX(Familias!B$2:B$17,MATCH(C6,Familias!A$2:A$17,0)) -> Restaurantes con servicio a mesa | E6: pollo asado, parrilla | F6: Pollos; Parrilladas; Acompañantes; Bebidas | G6: Platos | H6: Unidad
A7: T006 | B7: Parrillada / steakhouse | C7: F01 | D7: =INDEX(Familias!B$2:B$17,MATCH(C7,Familias!A$2:A$17,0)) -> Restaurantes con servicio a mesa | E7: carnes, parrilla | F7: Cortes; Parrilladas; Guarniciones; Bebidas | G7: Platos | H7: Unidad
A8: T007 | B8: Chifa | C8: F01 | D8: =INDEX(Familias!B$2:B$17,MATCH(C8,Familias!A$2:A$17,0)) -> Restaurantes con servicio a mesa | E8: comida china | F8: Arroces; Tallarines; Sopas; Bebidas | G8: Platos | H8: Unidad
A9: T008 | B9: Pizzería | C9: F01 | D9: =INDEX(Familias!B$2:B$17,MATCH(C9,Familias!A$2:A$17,0)) -> Restaurantes con servicio a mesa | E9: pizza | F9: Pizzas; Entradas; Bebidas; Postres | G9: Platos | H9: Unidad | I9: Tamaños de pizza como variantes
A10: T009 | B10: Restaurante de almuerzos (menú del día) | C10: F01 | D10: =INDEX(Familias!B$2:B$17,MATCH(C10,Familias!A$2:A$17,0)) -> Restaurantes con servicio a mesa | E10: almuerzos ejecutivos, comedor popular | F10: Almuerzos; Meriendas; Jugos | G10: Platos | H10: Unidad | I10: Menú del día cambiante
A11: T010 | B11: Encebollados y desayunos | C11: F01 | D11: =INDEX(Familias!B$2:B$17,MATCH(C11,Familias!A$2:A$17,0)) -> Restaurantes con servicio a mesa | E11: encebollado, bolones | F11: Encebollados; Bolones; Desayunos; Bebidas | G11: Platos | H11: Unidad
A12: T011 | B12: Fritadería / hornado | C12: F01 | D12: =INDEX(Familias!B$2:B$17,MATCH(C12,Familias!A$2:A$17,0)) -> Restaurantes con servicio a mesa | E12: fritada, hornado | F12: Fritada; Hornado; Acompañantes; Bebidas | G12: Platos | H12: Unidad
A13: T012 | B13: Sushi / comida japonesa | C13: F01 | D13: =INDEX(Familias!B$2:B$17,MATCH(C13,Familias!A$2:A$17,0)) -> Restaurantes con servicio a mesa | E13: sushi | F13: Rolls; Entradas; Bebidas | G13: Platos | H13: Unidad
A14: T013 | B14: Restaurante vegetariano | C14: F01 | D14: =INDEX(Familias!B$2:B$17,MATCH(C14,Familias!A$2:A$17,0)) -> Restaurantes con servicio a mesa | E14: vegano | F14: Platos; Ensaladas; Jugos; Postres | G14: Platos | H14: Unidad
A15: T014 | B15: Bar / cantina | C15: F01 | D15: =INDEX(Familias!B$2:B$17,MATCH(C15,Familias!A$2:A$17,0)) -> Restaurantes con servicio a mesa | E15: bar, cervecería | F15: Cervezas; Licores; Cócteles; Piqueos | G15: Platos | H15: Unidad
A16: T015 | B16: Discoteca | C16: F01 | D16: =INDEX(Familias!B$2:B$17,MATCH(C16,Familias!A$2:A$17,0)) -> Restaurantes con servicio a mesa | E16: club nocturno | F16: Botellas; Tragos; Cervezas; Entradas/cover | G16: Platos | H16: Unidad
A17: T016 | B17: Karaoke | C17: F01 | D17: =INDEX(Familias!B$2:B$17,MATCH(C17,Familias!A$2:A$17,0)) -> Restaurantes con servicio a mesa | E17: karaoke bar | F17: Bebidas; Piqueos; Horas de sala | G17: Platos | H17: Unidad
A18: T017 | B18: Restaurante de comida internacional | C18: F01 | D18: =INDEX(Familias!B$2:B$17,MATCH(C18,Familias!A$2:A$17,0)) -> Restaurantes con servicio a mesa | E18: mexicana, italiana | F18: Entradas; Platos fuertes; Bebidas; Postres | G18: Platos | H18: Unidad
A19: T018 | B19: Restaurante de hostería / campestre | C19: F01 | D19: =INDEX(Familias!B$2:B$17,MATCH(C19,Familias!A$2:A$17,0)) -> Restaurantes con servicio a mesa | E19: campestre | F19: Platos típicos; Parrilladas; Bebidas | G19: Platos | H19: Unidad
A20: T019 | B20: Comida rápida | C20: F02 | D20: =INDEX(Familias!B$2:B$17,MATCH(C20,Familias!A$2:A$17,0)) -> Comida rápida y para llevar | E20: fast food | F20: Hamburguesas; Hot dogs; Combos; Bebidas | G20: Productos | H20: Unidad
A21: T020 | B21: Hamburguesería | C21: F02 | D21: =INDEX(Familias!B$2:B$17,MATCH(C21,Familias!A$2:A$17,0)) -> Comida rápida y para llevar | E21: hamburguesas | F21: Hamburguesas; Papas; Combos; Bebidas | G21: Productos | H21: Unidad
A22: T021 | B22: Salchipapería | C22: F02 | D22: =INDEX(Familias!B$2:B$17,MATCH(C22,Familias!A$2:A$17,0)) -> Comida rápida y para llevar | E22: salchipapas | F22: Salchipapas; Combos; Bebidas | G22: Productos | H22: Unidad
... A34: T033 | B34: Panadería | C34: F03 | D34: =INDEX(Familias!B$2:B$17,MATCH(C34,Familias!A$2:A$17,0)) -> Panadería, pastelería y producción | E34: pan | F34: Panes; Pasteles; Bebidas; Lácteos | G34: Productos | H34: Unidad
A35: T034 | B35: Pastelería | C35: F03 | D35: =INDEX(Familias!B$2:B$17,MATCH(C35,Familias!A$2:A$17,0)) -> Panadería, pastelería y producción | E35: tortas, repostería | F35: Tortas; Postres; Bocaditos; Pedidos especiales | G35: Productos | H35: Unidad | I35: Pedidos con anticipo
A36: T035 | B36: Repostería en casa | C36: F03 | D36: =INDEX(Familias!B$2:B$17,MATCH(C36,Familias!A$2:A$17,0)) -> Panadería, pastelería y producción | E36: tortas por encargo | F36: Tortas; Cupcakes; Postres | G36: Productos | H36: Unidad | I36: Pedidos con anticipo
A37: T036 | B37: Chocolatería artesanal | C37: F03 | D37: =INDEX(Familias!B$2:B$17,MATCH(C37,Familias!A$2:A$17,0)) -> Panadería, pastelería y producción | E37: chocolates, cacao | F37: Barras; Bombones; Bebidas de cacao | G37: Productos | H37: Unidad
A38: T037 | B38: Fábrica de helados | C38: F03 | D38: =INDEX(Familias!B$2:B$17,MATCH(C38,Familias!A$2:A$17,0)) -> Panadería, pastelería y producción | E38: paletas | F38: Paletas; Litros; Conos | G38: Productos | H38: Unidad
A39: T038 | B39: Producción de snacks | C39: F03 | D39: =INDEX(Familias!B$2:B$17,MATCH(C39,Familias!A$2:A$17,0)) -> Panadería, pastelería y producción | E39: chifles, maduritos | F39: Chifles; Snacks; Paquetes | G39: Productos | H39: Unidad
A40: T039 | B40: Embutidos artesanales | C40: F03 | D40: =INDEX(Familias!B$2:B$17,MATCH(C40,Familias!A$2:A$17,0)) -> Panadería, pastelería y producción | E40: chorizos | F40: Embutidos; Carnes curadas | G40: Productos | H40: Kilo
A41: T040 | B41: Quesera / lácteos artesanales | C41: F03 | D41: =INDEX(Familias!B$2:B$17,MATCH(C41,Familias!A$2:A$17,0)) -> Panadería, pastelería y producción | E41: quesos, yogurt | F41: Quesos; Yogurt; Leche | G41: Productos | H41: Kilo
A42: T041 | B42: Cervecería artesanal | C42: F03 | D42: =INDEX(Familias!B$2:B$17,MATCH(C42,Familias!A$2:A$17,0)) -> Panadería, pastelería y producción | E42: cerveza artesanal | F42: Cervezas; Growlers; Barriles | G42: Productos | H42: Litro
A43: T042 | B43: Licores artesanales | C43: F03 | D43: =INDEX(Familias!B$2:B$17,MATCH(C43,Familias!A$2:A$17,0)) -> Panadería, pastelería y producción | E43: destilería | F43: Licores; Botellas | G43: Productos | H43: Botella
A44: T043 | B44: Mermeladas y conservas | C44: F03 | D44: =INDEX(Familias!B$2:B$17,MATCH(C44,Familias!A$2:A$17,0)) -> Panadería, pastelería y producción | E44: conservas | F44: Mermeladas; Conservas; Salsas | G44: Productos | H44: Unidad
A45: T044 | B45: Catering | C45: F03 | D45: =INDEX(Familias!B$2:B$17,MATCH(C45,Familias!A$2:A$17,0)) -> Panadería, pastelería y producción | E45: comida para eventos | F45: Menús; Bocaditos; Servicio | G45: Productos | H45: Unidad | I45: Cotizaciones por evento
A46: T045 | B46: Tienda de barrio | C46: F04 | D46: =INDEX(Familias!B$2:B$17,MATCH(C46,Familias!A$2:A$17,0)) -> Abarrotes y mercado | E46: tienda, abarrotes | F46: Abarrotes; Bebidas; Lácteos; Aseo; Snacks | G46: Productos | H46: Unidad
A47: T046 | B47: Minimarket | C47: F04 | D47: =INDEX(Familias!B$2:B$17,MATCH(C47,Familias!A$2:A$17,0)) -> Abarrotes y mercado | E47: minisúper | F47: Abarrotes; Bebidas; Lácteos; Aseo; Congelados | G47: Productos | H47: Unidad
A48: T047 | B48: Supermercado pequeño | C48: F04 | D48: =INDEX(Familias!B$2:B$17,MATCH(C48,Familias!A$2:A$17,0)) -> Abarrotes y mercado | E48: autoservicio | F48: Abarrotes; Frutas y verduras; Carnes; Aseo; Bebidas | G48: Productos | H48: Unidad
A49: T048 | B49: Despensa / víveres | C49: F04 | D49: =INDEX(Familias!B$2:B$17,MATCH(C49,Familias!A$2:A$17,0)) -> Abarrotes y mercado | E49: víveres | F49: Granos; Aceites; Enlatados; Aseo | G49: Productos | H49: Unidad
A50: T049 | B50: Frutería y verdulería | C50: F04 | D50: =INDEX(Familias!B$2:B$17,MATCH(C50,Familias!A$2:A$17,0)) -> Abarrotes y mercado | E50: frutas y verduras | F50: Frutas; Verduras; Tubérculos | G50: Productos | H50: Kilo
A51: T050 | B51: Carnicería / tercena | C51: F04 | D51: =INDEX(Familias!B$2:B$17,MATCH(C51,Familias!A$2:A$17,0)) -> Abarrotes y mercado | E51: carnes, tercena | F51: Res; Cerdo; Pollo; Embutidos | G51: Productos | H51: Libra
A52: T051 | B52: Pescadería | C52: F04 | D52: =INDEX(Familias!B$2:B$17,MATCH(C52,Familias!A$2:A$17,0)) -> Abarrotes y mercado | E52: mariscos, pescado | F52: Pescados; Camarón; Mariscos | G52: Productos | H52: Libra
A53: T052 | B53: Avícola / venta de pollos | C53: F04 | D53: =INDEX(Familias!B$2:B$17,MATCH(C53,Familias!A$2:A$17,0)) -> Abarrotes y mercado | E53: pollos, huevos | F53: Pollo entero; Presas; Huevos | G53: Productos | H53: Libra
A54: T053 | B54: Charcutería | C54: F04 | D54: =INDEX(Familias!B$2:B$17,MATCH(C54,Familias!A$2:A$17,0)) -> Abarrotes y mercado | E54: embutidos, quesos | F54: Embutidos; Quesos; Fiambres | G54: Productos | H54: Kilo
A55: T054 | B55: Licorería | C55: F04 | D55: =INDEX(Familias!B$2:B$17,MATCH(C55,Familias!A$2:A$17,0)) -> Abarrotes y mercado | E55: licores | F55: Cervezas; Licores; Vinos; Snacks | G55: Productos | H55: Unidad
A56: T055 | B56: Venta de agua y gas | C56: F04 | D56: =INDEX(Familias!B$2:B$17,MATCH(C56,Familias!A$2:A$17,0)) -> Abarrotes y mercado | E56: bidones, cilindros | F56: Agua; Gas; Recargas | G56: Productos | H56: Unidad | I56: Envases retornables
A57: T056 | B57: Tienda naturista | C57: F04 | D57: =INDEX(Familias!B$2:B$17,MATCH(C57,Familias!A$2:A$17,0)) -> Abarrotes y mercado | E57: productos naturales | F57: Suplementos; Hierbas; Granos | G57: Productos | H57: Unidad
A58: T057 | B58: Venta de huevos | C58: F04 | D58: =INDEX(Familias!B$2:B$17,MATCH(C58,Familias!A$2:A$17,0)) -> Abarrotes y mercado | E58: huevos | F58: Huevos; Cubetas | G58: Productos | H58: Cubeta
A59: T058 | B59: Puesto de mercado | C59: F04 | D59: =INDEX(Familias!B$2:B$17,MATCH(C59,Familias!A$2:A$17,0)) -> Abarrotes y mercado | E59: mercado municipal | F59: Productos del puesto | G59: Productos | H59: Kilo
A60: T059 | B60: Granos y cereales | C60: F04 | D60: =INDEX(Familias!B$2:B$17,MATCH(C60,Familias!A$2:A$17,0)) -> Abarrotes y mercado | E60: granos | F60: Arroz; Granos; Harinas | G60: Productos | H60: Quintal
A61: T060 | B61: Alimento para mascotas | C61: F04 | D61: =INDEX(Familias!B$2:B$17,MATCH(C61,Familias!A$2:A$17,0)) -> Abarrotes y mercado | E61: balanceado de mascotas | F61: Alimento perro; Alimento gato; Accesorios | G61: Productos | H61: Kilo
A62: T061 | B62: Tienda de ropa | C62: F05 | D62: =INDEX(Familias!B$2:B$17,MATCH(C62,Familias!A$2:A$17,0)) -> Moda y retail con variantes | E62: boutique, ropa | F62: Damas; Caballeros; Niños; Accesorios | G62: Productos | H62: Unidad
A63: T062 | B63: Zapatería | C63: F05 | D63: =INDEX(Familias!B$2:B$17,MATCH(C63,Familias!A$2:A$17,0)) -> Moda y retail con variantes | E63: zapatos, calzado | F63: Damas; Caballeros; Niños; Deportivo | G63: Productos | H63: Unidad
A64: T063 | B64: Ropa deportiva | C64: F05 | D64: =INDEX(Familias!B$2:B$17,MATCH(C64,Familias!A$2:A$17,0)) -> Moda y retail con variantes | E64: deportes | F64: Camisetas; Pantalonetas; Calzado; Accesorios | G64: Productos | H64: Unidad
A65: T064 | B65: Ropa de bebé y niños | C65: F05 | D65: =INDEX(Familias!B$2:B$17,MATCH(C65,Familias!A$2:A$17,0)) -> Moda y retail con variantes | E65: infantil | F65: Bebés; Niñas; Niños; Accesorios | G65: Productos | H65: Unidad
A66: T065 | B66: Lencería | C66: F05 | D66: =INDEX(Familias!B$2:B$17,MATCH(C66,Familias!A$2:A$17,0)) -> Moda y retail con variantes | E66: ropa interior | F66: Brasieres; Panties; Pijamas | G66: Productos | H66: Unidad
A67: T066 | B67: Uniformes | C67: F05 | D67: =INDEX(Familias!B$2:B$17,MATCH(C67,Familias!A$2:A$17,0)) -> Moda y retail con variantes | E67: uniformes escolares, corporativos | F67: Escolares; Corporativos; Deportivos | G67: Productos | H67: Unidad | I67: Pedidos por institución
A68: T067 | B68: Venta de ropa por redes | C68: F05 | D68: =INDEX(Familias!B$2:B$17,MATCH(C68,Familias!A$2:A$17,0)) -> Moda y retail con variantes | E68: venta por Instagram, TikTok | F68: Prendas; Accesorios | G68: Productos | H68: Unidad | I68: Catálogo online activo
A69: T068 | B69: Bolsos y carteras | C69: F05 | D69: =INDEX(Familias!B$2:B$17,MATCH(C69,Familias!A$2:A$17,0)) -> Moda y retail con variantes | E69: carteras | F69: Carteras; Mochilas; Billeteras | G69: Productos | H69: Unidad
A70: T069 | B70: Sastrería / trajes | C70: F05 | D70: =INDEX(Familias!B$2:B$17,MATCH(C70,Familias!A$2:A$17,0)) -> Moda y retail con variantes | E70: sastre, trajes | F70: Trajes; Camisas; Arreglos | G70: Productos | H70: Unidad | I70: Arreglos como servicio
A71: T070 | B71: Ropa de segunda mano | C71: F05 | D71: =INDEX(Familias!B$2:B$17,MATCH(C71,Familias!A$2:A$17,0)) -> Moda y retail con variantes | E71: ropa usada, americana | F71: Prendas; Calzado | G71: Productos | H71: Unidad
A72: T071 | B72: Óptica | C72: F05 | D72: =INDEX(Familias!B$2:B$17,MATCH(C72,Familias!A$2:A$17,0)) -> Moda y retail con variantes | E72: lentes, gafas | F72: Monturas; Lentes; Gafas de sol; Exámenes | G72: Productos | H72: Unidad
A73: T072 | B73: Joyería / bisutería | C73: F05 | D73: =INDEX(Familias!B$2:B$17,MATCH(C73,Familias!A$2:A$17,0)) -> Moda y retail con variantes | E73: joyas | F73: Anillos; Collares; Aretes; Relojes | G73: Productos | H73: Unidad
A74: T073 | B74: Bazar | C74: F06 | D74: =INDEX(Familias!B$2:B$17,MATCH(C74,Familias!A$2:A$17,0)) -> Retail general | E74: variedades | F74: Hogar; Plásticos; Regalos; Útiles | G74: Productos | H74: Unidad
A75: T074 | B75: Papelería y útiles escolares | C75: F06 | D75: =INDEX(Familias!B$2:B$17,MATCH(C75,Familias!A$2:A$17,0)) -> Retail general | E75: papelería | F75: Útiles; Cuadernos; Oficina; Copias | G75: Productos | H75: Unidad
A76: T075 | B76: Librería | C76: F06 | D76: =INDEX(Familias!B$2:B$17,MATCH(C76,Familias!A$2:A$17,0)) -> Retail general | E76: libros | F76: Libros; Revistas; Papelería | G76: Productos | H76: Unidad
A77: T076 | B77: Tienda de regalos | C77: F06 | D77: =INDEX(Familias!B$2:B$17,MATCH(C77,Familias!A$2:A$17,0)) -> Retail general | E77: regalos, detalles | F77: Regalos; Peluches; Tarjetas; Globos | G77: Productos | H77: Unidad
A78: T077 | B78: Juguetería | C78: F06 | D78: =INDEX(Familias!B$2:B$17,MATCH(C78,Familias!A$2:A$17,0)) -> Retail general | E78: juguetes | F78: Juguetes; Juegos; Didácticos | G78: Productos | H78: Unidad
A79: T078 | B79: Artículos para el hogar | C79: F06 | D79: =INDEX(Familias!B$2:B$17,MATCH(C79,Familias!A$2:A$17,0)) -> Retail general | E79: hogar | F79: Cocina; Baño; Decoración; Limpieza | G79: Productos | H79: Unidad
A80: T079 | B80: Plásticos y desechables | C80: F06 | D80: =INDEX(Familias!B$2:B$17,MATCH(C80,Familias!A$2:A$17,0)) -> Retail general | E80: desechables | F80: Desechables; Plásticos; Fundas | G80: Productos | H80: Unidad
A81: T080 | B81: Cosméticos y perfumería | C81: F06 | D81: =INDEX(Familias!B$2:B$17,MATCH(C81,Familias!A$2:A$17,0)) -> Retail general | E81: cosméticos, perfumes | F81: Maquillaje; Cuidado de piel; Perfumes | G81: Productos | H81: Unidad
A82: T081 | B82: Productos de limpieza | C82: F06 | D82: =INDEX(Familias!B$2:B$17,MATCH(C82,Familias!A$2:A$17,0)) -> Retail general | E82: químicos de limpieza | F82: Detergentes; Desinfectantes; Utensilios | G82: Productos | H82: Galón
A83: T082 | B83: Floristería | C83: F06 | D83: =INDEX(Familias!B$2:B$17,MATCH(C83,Familias!A$2:A$17,0)) -> Retail general | E83: flores, arreglos | F83: Arreglos; Ramos; Plantas | G83: Productos | H83: Unidad | I83: Pedidos con fecha de entrega
A84: T083 | B84: Artesanías | C84: F06 | D84: =INDEX(Familias!B$2:B$17,MATCH(C84,Familias!A$2:A$17,0)) -> Retail general | E84: artesanías | F84: Artesanías; Souvenirs | G84: Productos | H84: Unidad
A85: T084 | B85: Pet shop (accesorios) | C85: F06 | D85: =INDEX(Familias!B$2:B$17,MATCH(C85,Familias!A$2:A$17,0)) -> Retail general | E85: mascotas | F85: Accesorios; Juguetes; Higiene | G85: Productos | H85: Unidad
A86: T085 | B86: Artículos deportivos | C86: F06 | D86: =INDEX(Familias!B$2:B$17,MATCH(C86,Familias!A$2:A$17,0)) -> Retail general | E86: deportes | F86: Balones; Implementos; Ropa | G86: Productos | H86: Unidad
A87: T086 | B87: Mueblería | C87: F06 | D87: =INDEX(Familias!B$2:B$17,MATCH(C87,Familias!A$2:A$17,0)) -> Retail general | E87: muebles | F87: Salas; Comedores; Dormitorios | G87: Productos | H87: Unidad | I87: Venta a crédito
A88: T087 | B88: Colchones | C88: F06 | D88: =INDEX(Familias!B$2:B$17,MATCH(C88,Familias!A$2:A$17,0)) -> Retail general | E88: colchonería | F88: Colchones; Almohadas; Bases | G88: Productos | H88: Unidad
A89: T088 | B89: Accesorios de moda | C89: F06 | D89: =INDEX(Familias!B$2:B$17,MATCH(C89,Familias!A$2:A$17,0)) -> Retail general | E89: bisutería menor | F89: Aretes; Pulseras; Accesorios de cabello | G89: Productos | H89: Unidad
A90: T089 | B90: Artículos de fiesta | C90: F06 | D90: =INDEX(Familias!B$2:B$17,MATCH(C90,Familias!A$2:A$17,0)) -> Retail general | E90: cotillón | F90: Globos; Decoración; Piñatas | G90: Productos | H90: Unidad
A91: T090 | B91: Tabaquería / vape shop | C91: F06 | D91: =INDEX(Familias!B$2:B$17,MATCH(C91,Familias!A$2:A$17,0)) -> Retail general | E91: tabaco | F91: Productos; Accesorios | G91: Productos | H91: Unidad
A92: T091 | B92: Souvenirs turísticos | C92: F06 | D92: =INDEX(Familias!B$2:B$17,MATCH(C92,Familias!A$2:A$17,0)) -> Retail general | E92: recuerdos | F92: Souvenirs; Camisetas; Artesanías | G92: Productos | H92: Unidad
A93: T092 | B93: Bicicletas | C93: F06 | D93: =INDEX(Familias!B$2:B$17,MATCH(C93,Familias!A$2:A$17,0)) -> Retail general | E93: bici | F93: Bicicletas; Repuestos; Accesorios | G93: Productos | H93: Unidad
A94: T093 | B94: Farmacia | C94: F07 | D94: =INDEX(Familias!B$2:B$17,MATCH(C94,Familias!A$2:A$17,0)) -> Farmacia y salud con producto | E94: botica | F94: Medicamentos; Cuidado personal; Bebé; Primeros auxilios | G94: Productos | H94: Unidad | I94: Venta por unidad o caja (fracción)
A95: T094 | B95: Farmacia veterinaria | C95: F07 | D95: =INDEX(Familias!B$2:B$17,MATCH(C95,Familias!A$2:A$17,0)) -> Farmacia y salud con producto | E95: veterinaria de mascotas | F95: Medicamentos; Vacunas; Alimentos | G95: Productos | H95: Unidad
A96: T095 | B96: Insumos médicos | C96: F07 | D96: =INDEX(Familias!B$2:B$17,MATCH(C96,Familias!A$2:A$17,0)) -> Farmacia y salud con producto | E96: distribuidora médica | F96: Insumos; Equipos; Descartables | G96: Productos | H96: Unidad
A97: T096 | B97: Suplementos deportivos | C97: F07 | D97: =INDEX(Familias!B$2:B$17,MATCH(C97,Familias!A$2:A$17,0)) -> Farmacia y salud con producto | E97: proteína, nutrición deportiva | F97: Proteínas; Vitaminas; Snacks | G97: Productos | H97: Unidad
A98: T097 | B98: Ortopedia | C98: F07 | D98: =INDEX(Familias!B$2:B$17,MATCH(C98,Familias!A$2:A$17,0)) -> Farmacia y salud con producto | E98: artículos ortopédicos | F98: Plantillas; Fajas; Sillas de ruedas | G98: Productos | H98: Unidad
A99: T098 | B99: Homeopatía / productos naturales | C99: F07 | D99: =INDEX(Familias!B$2:B$17,MATCH(C99,Familias!A$2:A$17,0)) -> Farmacia y salud con producto | E99: naturista | F99: Suplementos; Tés; Aceites | G99: Productos | H99: Unidad
A100: T099 | B100: Tienda de celulares | C100: F08 | D100: =INDEX(Familias!B$2:B$17,MATCH(C100,Familias!A$2:A$17,0)) -> Tecnología y electrónica | E100: celulares, móviles | F100: Celulares; Accesorios; Chips; Recargas | G100: Productos | H100: Unidad | I100: IMEI obligatorio
A101: T100 | B101: Accesorios para celulares | C101: F08 | D101: =INDEX(Familias!B$2:B$17,MATCH(C101,Familias!A$2:A$17,0)) -> Tecnología y electrónica | E101: fundas, cargadores | F101: Fundas; Cargadores; Audífonos; Micas | G101: Productos | H101: Unidad
A102: T101 | B102: Computadoras | C102: F08 | D102: =INDEX(Familias!B$2:B$17,MATCH(C102,Familias!A$2:A$17,0)) -> Tecnología y electrónica | E102: computación | F102: Laptops; Componentes; Periféricos | G102: Productos | H102: Unidad
A103: T102 | B103: Electrodomésticos | C103: F08 | D103: =INDEX(Familias!B$2:B$17,MATCH(C103,Familias!A$2:A$17,0)) -> Tecnología y electrónica | E103: línea blanca | F103: Refrigeración; Cocina; Lavado; Pequeños | G103: Productos | H103: Unidad | I103: Venta a crédito
A104: T103 | B104: Videojuegos | C104: F08 | D104: =INDEX(Familias!B$2:B$17,MATCH(C104,Familias!A$2:A$17,0)) -> Tecnología y electrónica | E104: gaming | F104: Consolas; Juegos; Accesorios | G104: Productos | H104: Unidad
A105: T104 | B105: Cámaras de seguridad / CCTV | C105: F08 | D105: =INDEX(Familias!B$2:B$17,MATCH(C105,Familias!A$2:A$17,0)) -> Tecnología y electrónica | E105: seguridad electrónica | F105: Cámaras; DVR; Instalación | G105: Productos | H105: Unidad
A106: T105 | B106: Cyber / centro de cómputo | C106: F08 | D106: =INDEX(Familias!B$2:B$17,MATCH(C106,Familias!A$2:A$17,0)) -> Tecnología y electrónica | E106: internet, copias | F106: Horas de internet; Impresiones; Copias | G106: Productos | H106: Unidad | I106: Cobro por tiempo
A107: T106 | B107: Recargas y pagos de servicios | C107: F08 | D107: =INDEX(Familias!B$2:B$17,MATCH(C107,Familias!A$2:A$17,0)) -> Tecnología y electrónica | E107: punto de recargas | F107: Recargas; Pagos de servicios; Chips | G107: Productos | H107: Unidad | I107: Comisión por transacción
A108: T107 | B108: Electrónica y componentes | C108: F08 | D108: =INDEX(Familias!B$2:B$17,MATCH(C108,Familias!A$2:A$17,0)) -> Tecnología y electrónica | E108: componentes electrónicos | F108: Componentes; Cables; Herramientas | G108: Productos | H108: Unidad
A109: T108 | B109: Energía solar | C109: F08 | D109: =INDEX(Familias!B$2:B$17,MATCH(C109,Familias!A$2:A$17,0)) -> Tecnología y electrónica | E109: paneles solares | F109: Paneles; Baterías; Inversores; Instalación | G109: Productos | H109: Unidad
A110: T109 | B110: Ferretería | C110: F09 | D110: =INDEX(Familias!B$2:B$17,MATCH(C110,Familias!A$2:A$17,0)) -> Ferretería y construcción | E110: ferretería | F110: Herramientas; Tornillería; Plomería; Eléctricos; Pintura | G110: Productos | H110: Unidad
A111: T110 | B111: Materiales de construcción | C111: F09 | D111: =INDEX(Familias!B$2:B$17,MATCH(C111,Familias!A$2:A$17,0)) -> Ferretería y construcción | E111: bloques, cemento | F111: Cemento; Hierro; Bloques; Arena | G111: Productos | H111: Quintal
...

Sheet Fichas ejemplo
A1: Tipo de negocio | B1: Categoría | C1: Producto / servicio de ejemplo | D1: Unidad / variantes
A2: Tienda de barrio | B2: Abarrotes | C2: Arroz 1 kg | D2: Unidad
A3: Tienda de barrio | B3: Abarrotes | C3: Azúcar 1 kg | D3: Unidad
A4: Tienda de barrio | B4: Abarrotes | C4: Aceite 1 L | D4: Unidad
A5: Tienda de barrio | B5: Abarrotes | C5: Atún en lata | D5: Unidad
A6: Tienda de barrio | B6: Bebidas | C6: Gaseosa 1.35 L | D6: Unidad
A7: Tienda de barrio | B7: Bebidas | C7: Agua 625 ml | D7: Unidad
A8: Tienda de barrio | B8: Lácteos | C8: Leche 1 L | D8: Unidad
A9: Tienda de barrio | B9: Lácteos | C9: Queso fresco | D9: Libra
A10: Tienda de barrio | B10: Aseo | C10: Papel higiénico x4 | D10: Unidad
A11: Tienda de barrio | B11: Aseo | C11: Detergente 500 g | D11: Unidad
A12: Tienda de barrio | B12: Snacks | C12: Papas fritas | D12: Unidad
... A63: Tienda de ropa | B63: Accesorios | C63: Gorra | D63: Unidad
A65: Sin precios: el usuario pone los suyos o la IA sugiere referencias durante el alta. Estas 6 fichas muestran el formato; el resto se genera igual.

Sheet Flujo de registro
A1: Paso | B1: Pantalla | C1: Qué ve o responde el usuario | D1: Qué hace el sistema
A2: 1 | B2: Número de celular | C2: ¿Cuál es tu número? | D2: Envía un código por WhatsApp; crea el usuario sin contraseña
A3: 2 | B3: Código | C3: Ingresa el código de 6 dígitos | D3: Valida y abre sesión
A4: 3 | B4: Tipo de negocio | C4: ¿Qué negocio tienes? (buscador con sugerencias) | D4: Busca por nombre y sinónimos en la hoja Tipos de negocio; si no hay coincidencia, la IA asigna la familia más cercana y genera la ficha
A5: 4 | B5: Nombre del negocio | C5: ¿Cómo se llama tu negocio? | D5: Crea el negocio y aplica la familia: activa los módulos marcados S
A6: 5 | B6: RUC (opcional) | C6: ¿Tienes RUC? (se puede saltar) | D6: Consulta el SRI: razón social, régimen RIMPE o general, dirección; deja lista la facturación
A7: 6 | B7: Carga inicial | C7: (automático) | D7: Crea categorías y productos de ejemplo de la ficha, unidades, vocabulario y métodos de pago de Ecuador
A8: 7 | B8: Entrada al sistema | C8: (automático) | D8: Abre directo en la pantalla de venta; tour de 3 pasos según la familia
A9: 8 | B9: Después | C9: Sugerencias en el panel | D9: Ofrece activar módulos opcionales (O) cuando el uso lo indique; por ejemplo, fiado si registra ventas a crédito
